spelling_bee_cheat/__init__.py
spelling_bee_cheat/dictionary.py
spelling_bee_cheat/dictionary_search.py
spelling_bee_cheat/folders.py
spelling_bee_cheat/markov_search.py
spelling_bee_cheat/nyt_scraping.py
spelling_bee_cheat/archive/__init__.py
spelling_bee_cheat/archive/archive.py
spelling_bee_cheat/data_model/__init__.py
spelling_bee_cheat/data_model/puzzle.py
spelling_bee_cheat/scrape/__init__.py
spelling_bee_cheat/scrape/scrape.py
spelling_bee_cheat/scripts/convert_archive.py
spelling_bee_cheat/scripts/markov.py
spelling_bee_cheat/scripts/scrape.py
spelling_bee_cheat-0.0.1.dist-info/LICENSE
spelling_bee_cheat-0.0.1.dist-info/METADATA
spelling_bee_cheat-0.0.1.dist-info/WHEEL
spelling_bee_cheat-0.0.1.dist-info/entry_points.txt
spelling_bee_cheat-0.0.1.dist-info/top_level.txt
spelling_bee_cheat-0.0.1.dist-info/RECORD
