Metadata-Version: 2.1
Name: spelling-bee-cheat
Version: 0.0.1
Summary: Cheat at the NYT Spelling Bee.
Author-email: James Hoctor <jehoctor@protonmail.com>
License: MIT License
Project-URL: Homepage, https://github.com/JEHoctor/spelling-bee-cheat
Classifier: Programming Language :: Python :: 3
Classifier: License :: OSI Approved :: MIT License
License-File: LICENSE
Requires-Dist: beautifulsoup4
Requires-Dist: click
Requires-Dist: more-itertools
Requires-Dist: nltk
Requires-Dist: numpy
Requires-Dist: pandas
Requires-Dist: scikit-learn
Requires-Dist: spacy
Requires-Dist: transformers
Provides-Extra: dev
Requires-Dist: black ; extra == 'dev'
Requires-Dist: build ; extra == 'dev'
Requires-Dist: isort ; extra == 'dev'
Requires-Dist: jupyter ; extra == 'dev'
Requires-Dist: pip-tools ; extra == 'dev'
Requires-Dist: pytest ; extra == 'dev'
Requires-Dist: ruff ; extra == 'dev'
Requires-Dist: seaborn ; extra == 'dev'
Requires-Dist: twine ; extra == 'dev'
